{
    "host": "localhost",
    "port": 3030,
    "public": "../public/",
    "paginate": {
        "default": 10,
        "max": 50
    },
    "authentication": {
        "entity": "user",
        "service": "users",
        "secret": "demwgh4moebtwsS52ifbfR9Cl3c=",
        "authStrategies": [
            "jwt",
            "local"
        ],
        "jwtOptions": {
            "header": {
                "typ": "access"
            },
            "audience": "https://yourdomain.com",
            "issuer": "feathers",
            "algorithm": "HS256",
            "expiresIn": "1d"
        },
        "local": {
            "usernameField": "email",
            "passwordField": "password"
        }
    },
    "mongodb": "mongodb+srv://aagam_0304:kz8dbflfevuvh8u5@cluster0.fjjfw.mongodb.net/Employee_Tracker?retryWrites=true&w=majority"
}